terraqt/__init__.py
terraqt/_version.py
terraqt/client.py
terraqt/config.py
terraqt/core.py
terraqt/locations.py
terraqt/models.py
terraqt/py.typed
terraqt_client-0.0.1.dist-info/METADATA
terraqt_client-0.0.1.dist-info/WHEEL
terraqt_client-0.0.1.dist-info/licenses/LICENSE
terraqt_client-0.0.1.dist-info/RECORD
