Metadata-Version: 2.4
Name: terraqt-client
Version: 0.0.1
Summary: TrerraQT Query Client
Project-URL: Homepage, https://github.com/terraqt/terraqt-client
Project-URL: Repository, https://github.com/jed-cheng/terraqt-client.git
Project-URL: Issues, https://github.com/terraqt/terraqt-client/issues
Author: Jed Cheng
License: MIT
License-File: LICENSE
Keywords: api,async,forecast,sdk,terraqt,weather
Classifier: Development Status :: 4 - Beta
Classifier: Framework :: AsyncIO
Classifier: Intended Audience :: Developers
Classifier: License :: OSI Approved :: MIT License
Classifier: Operating System :: OS Independent
Classifier: Programming Language :: Python :: 3
Classifier: Programming Language :: Python :: 3.11
Classifier: Programming Language :: Python :: 3.12
Classifier: Programming Language :: Python :: 3.13
Classifier: Typing :: Typed
Requires-Python: >=3.11
Requires-Dist: aiohttp>=3.9.0
Requires-Dist: numpy>=1.26.0
Requires-Dist: pandas>=2.1.0
Provides-Extra: all
Requires-Dist: mkdocs-material>=9.5.0; extra == 'all'
Requires-Dist: mkdocs>=1.5.0; extra == 'all'
Requires-Dist: mkdocstrings[python]>=0.24.0; extra == 'all'
Requires-Dist: mypy>=1.8.0; extra == 'all'
Requires-Dist: pandas-stubs>=2.1.0; extra == 'all'
Requires-Dist: pymysql>=1.1.0; extra == 'all'
Requires-Dist: pytest-asyncio>=0.23.0; extra == 'all'
Requires-Dist: pytest-cov>=4.1.0; extra == 'all'
Requires-Dist: pytest>=8.0.0; extra == 'all'
Requires-Dist: python-dotenv>=1.2.1; extra == 'all'
Requires-Dist: ruff>=0.2.0; extra == 'all'
Requires-Dist: sqlalchemy>=2.0.0; extra == 'all'
Requires-Dist: types-aiofiles>=23.2.0; extra == 'all'
Provides-Extra: db
Requires-Dist: pymysql>=1.1.0; extra == 'db'
Requires-Dist: python-dotenv>=1.2.1; extra == 'db'
Requires-Dist: sqlalchemy>=2.0.0; extra == 'db'
Provides-Extra: dev
Requires-Dist: mypy>=1.8.0; extra == 'dev'
Requires-Dist: pandas-stubs>=2.1.0; extra == 'dev'
Requires-Dist: pytest-asyncio>=0.23.0; extra == 'dev'
Requires-Dist: pytest-cov>=4.1.0; extra == 'dev'
Requires-Dist: pytest>=8.0.0; extra == 'dev'
Requires-Dist: ruff>=0.2.0; extra == 'dev'
Requires-Dist: types-aiofiles>=23.2.0; extra == 'dev'
Provides-Extra: docs
Requires-Dist: mkdocs-material>=9.5.0; extra == 'docs'
Requires-Dist: mkdocs>=1.5.0; extra == 'docs'
Requires-Dist: mkdocstrings[python]>=0.24.0; extra == 'docs'
